LICENSE
MANIFEST.in
README.md
README.pypi
pyproject.toml
requirements.txt
setup.py
Orange3_spatial.egg-info/PKG-INFO
Orange3_spatial.egg-info/SOURCES.txt
Orange3_spatial.egg-info/dependency_links.txt
Orange3_spatial.egg-info/entry_points.txt
Orange3_spatial.egg-info/namespace_packages.txt
Orange3_spatial.egg-info/not-zip-safe
Orange3_spatial.egg-info/requires.txt
Orange3_spatial.egg-info/top_level.txt
orangecontrib/__init__.py
orangecontrib/spatial/__init__.py
orangecontrib/spatial/utils/__init__.py
orangecontrib/spatial/utils/spectroscopy/README.txt
orangecontrib/spatial/utils/spectroscopy/__init__.py
orangecontrib/spatial/widgets/__init__.py
orangecontrib/spatial/widgets/owclusterconnectivity.py
orangecontrib/spatial/widgets/owconsensuscluster.py
orangecontrib/spatial/widgets/icons/category.svg
orangecontrib/spatial/widgets/icons/cluster_connectivity.svg
orangecontrib/spatial/widgets/icons/consensus_cluster.svg